core_helpers/__init__.py
core_helpers/api/__init__.py
core_helpers/api/filters/__init__.py
core_helpers/api/serializers/__init__.py
core_helpers/api/views/__init__.py
core_helpers/db/__init__.py
core_helpers/db/fields/__init__.py
core_helpers/db/fields/core.py
core_helpers/db/managers/__init__.py
core_helpers/db/managers/core.py
core_helpers/db/models/__init__.py
core_helpers/db/models/core.py
django_core_helpers-0.1.2.dist-info/LICENSE
django_core_helpers-0.1.2.dist-info/WHEEL
django_core_helpers-0.1.2.dist-info/METADATA
django_core_helpers-0.1.2.dist-info/RECORD
